MANIFEST.in
README.md
setup.py
datagoose/__init__.py
datagoose/encryption.py
datagoose/errors.py
datagoose/functions.py
datagoose.egg-info/PKG-INFO
datagoose.egg-info/SOURCES.txt
datagoose.egg-info/dependency_links.txt
datagoose.egg-info/requires.txt
datagoose.egg-info/top_level.txt