Metadata-Version: 2.1
Name: datagoose
Version: 1.6.0
Summary: Easy to use 👋 fast & lightweight ☄️ secure 🔐 JSON based database for python! 🐍.
Home-page: https://github.com/5elenay/datagoose/
Author: 5elenay
Author-email: 
License: GNU General Public License v3 (GPLv3)
Project-URL: Bug Tracker, https://github.com/5elenay/datagoose/issues
Keywords: database,lightweight,json,python-database,json-database,fast,secure
Platform: UNKNOWN
Classifier: Development Status :: 3 - Alpha
Classifier: Intended Audience :: Developers
Classifier: Operating System :: OS Independent
Classifier: License :: OSI Approved :: GNU General Public License v3 (GPLv3)
Classifier: Programming Language :: Python :: 3
